[
  {
    "id": "1776123551559-oqwp61vhq",
    "timestamp": "2026-04-13T23:39:11.559Z",
    "level": "info",
    "category": "SYSTEM",
    "message": "System: service_test",
    "metadata": {
      "event": "service_test",
      "service": "smtp",
      "status": "up",
      "latency": 193
    }
  },
  {
    "id": "1776123550195-qp7uwkcll",
    "timestamp": "2026-04-13T23:39:10.195Z",
    "level": "info",
    "category": "SYSTEM",
    "message": "System: service_test",
    "metadata": {
      "event": "service_test",
      "service": "database",
      "latency": 3
    }
  },
  {
    "id": "1776123549079-kt2zorxic",
    "timestamp": "2026-04-13T23:39:09.079Z",
    "level": "info",
    "category": "SYSTEM",
    "message": "System: service_test",
    "metadata": {
      "event": "service_test",
      "service": "ldap",
      "status": "up",
      "latency": 2
    }
  },
  {
    "id": "1776123547836-hjjh6oa2g",
    "timestamp": "2026-04-13T23:39:07.836Z",
    "level": "info",
    "category": "SYSTEM",
    "message": "System: service_test",
    "metadata": {
      "event": "service_test",
      "service": "authentik",
      "status": "up",
      "latency": 164
    }
  },
  {
    "id": "1776123544085-9wtzcomkp",
    "timestamp": "2026-04-13T23:39:04.085Z",
    "level": "info",
    "category": "SYSTEM",
    "message": "System: service_test",
    "metadata": {
      "event": "service_test",
      "service": "ldap",
      "status": "up",
      "latency": 3
    }
  },
  {
    "id": "1776123542790-0f16orlhq",
    "timestamp": "2026-04-13T23:39:02.790Z",
    "level": "info",
    "category": "SYSTEM",
    "message": "System: service_test",
    "metadata": {
      "event": "service_test",
      "service": "authentik",
      "status": "up",
      "latency": 157
    }
  },
  {
    "id": "1776107787945-3x4rrresi",
    "timestamp": "2026-04-13T19:16:27.945Z",
    "level": "info",
    "category": "SYSTEM",
    "message": "System: health_check",
    "metadata": {
      "event": "health_check",
      "overallStatus": "healthy",
      "responseTime": 193,
      "services": {
        "authentik": "up",
        "ldap": "up",
        "database": "up",
        "smtp": "up"
      }
    }
  },
  {
    "id": "1776105530918-5n0w9twrt",
    "timestamp": "2026-04-13T18:38:50.918Z",
    "level": "info",
    "category": "SYSTEM",
    "message": "System: health_check",
    "metadata": {
      "event": "health_check",
      "overallStatus": "healthy",
      "responseTime": 228,
      "services": {
        "authentik": "up",
        "ldap": "up",
        "database": "up",
        "smtp": "down"
      }
    }
  },
  {
    "id": "1776099748478-71ey7yq7f",
    "timestamp": "2026-04-13T17:02:28.478Z",
    "level": "info",
    "category": "SYSTEM",
    "message": "System: health_check",
    "metadata": {
      "event": "health_check",
      "overallStatus": "healthy",
      "responseTime": 15022,
      "services": {
        "authentik": "up",
        "ldap": "up",
        "database": "up",
        "smtp": "down"
      }
    }
  },
  {
    "id": "1776091616567-s05i14okc",
    "timestamp": "2026-04-13T14:46:56.567Z",
    "level": "info",
    "category": "SYSTEM",
    "message": "System: health_check",
    "metadata": {
      "event": "health_check",
      "overallStatus": "healthy",
      "responseTime": 247,
      "services": {
        "authentik": "up",
        "ldap": "up",
        "database": "up",
        "smtp": "up"
      }
    }
  },
  {
    "id": "1776091301930-i9uhedlar",
    "timestamp": "2026-04-13T14:41:41.930Z",
    "level": "info",
    "category": "SYSTEM",
    "message": "System: health_check",
    "metadata": {
      "event": "health_check",
      "overallStatus": "healthy",
      "responseTime": 189,
      "services": {
        "authentik": "up",
        "ldap": "up",
        "database": "up",
        "smtp": "up"
      }
    }
  },
  {
    "id": "1776091268913-k4zunykln",
    "timestamp": "2026-04-13T14:41:08.913Z",
    "level": "info",
    "category": "SYSTEM",
    "message": "System: health_check",
    "metadata": {
      "event": "health_check",
      "overallStatus": "healthy",
      "responseTime": 180,
      "services": {
        "authentik": "up",
        "ldap": "up",
        "database": "up",
        "smtp": "up"
      }
    }
  },
  {
    "id": "1776011859491-ha5n3n26g",
    "timestamp": "2026-04-12T16:37:39.491Z",
    "level": "info",
    "category": "SYSTEM",
    "message": "System: health_check",
    "metadata": {
      "event": "health_check",
      "overallStatus": "healthy",
      "responseTime": 1337,
      "services": {
        "authentik": "up",
        "ldap": "up",
        "database": "up",
        "smtp": "up"
      }
    }
  },
  {
    "id": "1775961602349-f9skom6az",
    "timestamp": "2026-04-12T02:40:02.349Z",
    "level": "info",
    "category": "SYSTEM",
    "message": "System: health_check",
    "metadata": {
      "event": "health_check",
      "overallStatus": "healthy",
      "responseTime": 540,
      "services": {
        "authentik": "up",
        "ldap": "up",
        "database": "up",
        "smtp": "up"
      }
    }
  },
  {
    "id": "1775961598831-hzts67c6j",
    "timestamp": "2026-04-12T02:39:58.831Z",
    "level": "info",
    "category": "SYSTEM",
    "message": "System: health_check",
    "metadata": {
      "event": "health_check",
      "overallStatus": "healthy",
      "responseTime": 6468,
      "services": {
        "authentik": "up",
        "ldap": "up",
        "database": "up",
        "smtp": "up"
      }
    }
  },
  {
    "id": "1775891593891-regkjvil2",
    "timestamp": "2026-04-11T07:13:13.891Z",
    "level": "info",
    "category": "SYSTEM",
    "message": "System: health_check",
    "metadata": {
      "event": "health_check",
      "overallStatus": "healthy",
      "responseTime": 5506,
      "services": {
        "authentik": "up",
        "ldap": "up",
        "database": "up",
        "smtp": "up"
      }
    }
  },
  {
    "id": "1775856560807-prwh7jd8k",
    "timestamp": "2026-04-10T21:29:20.807Z",
    "level": "info",
    "category": "SYSTEM",
    "message": "System: health_check",
    "metadata": {
      "event": "health_check",
      "overallStatus": "healthy",
      "responseTime": 3581,
      "services": {
        "authentik": "up",
        "ldap": "up",
        "database": "up",
        "smtp": "up"
      }
    }
  },
  {
    "id": "1775850726485-9cz2bufbq",
    "timestamp": "2026-04-10T19:52:06.485Z",
    "level": "info",
    "category": "SYSTEM",
    "message": "System: health_check",
    "metadata": {
      "event": "health_check",
      "overallStatus": "healthy",
      "responseTime": 8674,
      "services": {
        "authentik": "up",
        "ldap": "up",
        "database": "up",
        "smtp": "up"
      }
    }
  },
  {
    "id": "1775744140292-pfopwi5ht",
    "timestamp": "2026-04-09T14:15:40.292Z",
    "level": "info",
    "category": "SYSTEM",
    "message": "System: health_check",
    "metadata": {
      "event": "health_check",
      "overallStatus": "healthy",
      "responseTime": 7853,
      "services": {
        "authentik": "up",
        "ldap": "up",
        "database": "up",
        "smtp": "up"
      }
    }
  },
  {
    "id": "1775714766371-wasi4ey48",
    "timestamp": "2026-04-09T06:06:06.371Z",
    "level": "info",
    "category": "SYSTEM",
    "message": "System: health_check",
    "metadata": {
      "event": "health_check",
      "overallStatus": "healthy",
      "responseTime": 7643,
      "services": {
        "authentik": "up",
        "ldap": "up",
        "database": "up",
        "smtp": "up"
      }
    }
  },
  {
    "id": "1775645060642-ku2mgbc8g",
    "timestamp": "2026-04-08T10:44:20.642Z",
    "level": "info",
    "category": "SYSTEM",
    "message": "System: health_check",
    "metadata": {
      "event": "health_check",
      "overallStatus": "healthy",
      "responseTime": 6006,
      "services": {
        "authentik": "up",
        "ldap": "up",
        "database": "up",
        "smtp": "up"
      }
    }
  },
  {
    "id": "1775629019392-wnotvg68t",
    "timestamp": "2026-04-08T06:16:59.392Z",
    "level": "info",
    "category": "SYSTEM",
    "message": "System: service_test",
    "metadata": {
      "event": "service_test",
      "service": "smtp",
      "status": "up",
      "latency": 1751
    }
  },
  {
    "id": "1775628856698-p45m69h09",
    "timestamp": "2026-04-08T06:14:16.698Z",
    "level": "info",
    "category": "SYSTEM",
    "message": "System: health_check",
    "metadata": {
      "event": "health_check",
      "overallStatus": "healthy",
      "responseTime": 4480,
      "services": {
        "authentik": "up",
        "ldap": "up",
        "database": "up",
        "smtp": "up"
      }
    }
  },
  {
    "id": "1775628748871-pdrscfoqp",
    "timestamp": "2026-04-08T06:12:28.871Z",
    "level": "info",
    "category": "SYSTEM",
    "message": "System: health_check",
    "metadata": {
      "event": "health_check",
      "overallStatus": "healthy",
      "responseTime": 6105,
      "services": {
        "authentik": "up",
        "ldap": "up",
        "database": "up",
        "smtp": "up"
      }
    }
  },
  {
    "id": "1775624160451-zh2e0gwcp",
    "timestamp": "2026-04-08T04:56:00.451Z",
    "level": "info",
    "category": "SYSTEM",
    "message": "System: health_check",
    "metadata": {
      "event": "health_check",
      "overallStatus": "healthy",
      "responseTime": 4917,
      "services": {
        "authentik": "up",
        "ldap": "up",
        "database": "up",
        "smtp": "up"
      }
    }
  },
  {
    "id": "1775623550861-vb4d063n0",
    "timestamp": "2026-04-08T04:45:50.861Z",
    "level": "info",
    "category": "SYSTEM",
    "message": "System: health_check",
    "metadata": {
      "event": "health_check",
      "overallStatus": "healthy",
      "responseTime": 6613,
      "services": {
        "authentik": "up",
        "ldap": "up",
        "database": "up",
        "smtp": "up"
      }
    }
  },
  {
    "id": "1775594287300-g9awdj8bd",
    "timestamp": "2026-04-07T20:38:07.300Z",
    "level": "info",
    "category": "SYSTEM",
    "message": "System: health_check",
    "metadata": {
      "event": "health_check",
      "overallStatus": "healthy",
      "responseTime": 1952,
      "services": {
        "authentik": "up",
        "ldap": "up",
        "database": "up",
        "smtp": "up"
      }
    }
  },
  {
    "id": "1775593936863-3uy6r79jq",
    "timestamp": "2026-04-07T20:32:16.863Z",
    "level": "info",
    "category": "SYSTEM",
    "message": "System: health_check",
    "metadata": {
      "event": "health_check",
      "overallStatus": "healthy",
      "responseTime": 1790,
      "services": {
        "authentik": "up",
        "ldap": "up",
        "database": "up",
        "smtp": "up"
      }
    }
  },
  {
    "id": "1775593613447-fyaevbbx6",
    "timestamp": "2026-04-07T20:26:53.447Z",
    "level": "info",
    "category": "SYSTEM",
    "message": "System: health_check",
    "metadata": {
      "event": "health_check",
      "overallStatus": "healthy",
      "responseTime": 8628,
      "services": {
        "authentik": "up",
        "ldap": "up",
        "database": "up",
        "smtp": "up"
      }
    }
  },
  {
    "id": "1775592626960-x6hbug9ah",
    "timestamp": "2026-04-07T20:10:26.960Z",
    "level": "info",
    "category": "SYSTEM",
    "message": "System: health_check",
    "metadata": {
      "event": "health_check",
      "overallStatus": "healthy",
      "responseTime": 505,
      "services": {
        "authentik": "up",
        "ldap": "up",
        "database": "up",
        "smtp": "up"
      }
    }
  },
  {
    "id": "1775592606602-klbmx1t3r",
    "timestamp": "2026-04-07T20:10:06.602Z",
    "level": "info",
    "category": "SYSTEM",
    "message": "System: health_check",
    "metadata": {
      "event": "health_check",
      "overallStatus": "healthy",
      "responseTime": 577,
      "services": {
        "authentik": "up",
        "ldap": "up",
        "database": "up",
        "smtp": "up"
      }
    }
  },
  {
    "id": "1775592571574-wqcckm2n9",
    "timestamp": "2026-04-07T20:09:31.574Z",
    "level": "info",
    "category": "SYSTEM",
    "message": "System: health_check",
    "metadata": {
      "event": "health_check",
      "overallStatus": "healthy",
      "responseTime": 4653,
      "services": {
        "authentik": "up",
        "ldap": "up",
        "database": "up",
        "smtp": "up"
      }
    }
  },
  {
    "id": "1775592350376-0myh8omom",
    "timestamp": "2026-04-07T20:05:50.376Z",
    "level": "info",
    "category": "SYSTEM",
    "message": "System: health_check",
    "metadata": {
      "event": "health_check",
      "overallStatus": "healthy",
      "responseTime": 531,
      "services": {
        "authentik": "up",
        "ldap": "up",
        "database": "up",
        "smtp": "up"
      }
    }
  },
  {
    "id": "1775592247103-khnkbotyu",
    "timestamp": "2026-04-07T20:04:07.103Z",
    "level": "info",
    "category": "SYSTEM",
    "message": "System: health_check",
    "metadata": {
      "event": "health_check",
      "overallStatus": "healthy",
      "responseTime": 2300,
      "services": {
        "authentik": "up",
        "ldap": "up",
        "database": "up",
        "smtp": "up"
      }
    }
  },
  {
    "id": "1775592164742-000a8ikc7",
    "timestamp": "2026-04-07T20:02:44.742Z",
    "level": "info",
    "category": "SYSTEM",
    "message": "System: health_check",
    "metadata": {
      "event": "health_check",
      "overallStatus": "healthy",
      "responseTime": 5769,
      "services": {
        "authentik": "up",
        "ldap": "up",
        "database": "up",
        "smtp": "up"
      }
    }
  },
  {
    "id": "1775591440602-ic32pxb5y",
    "timestamp": "2026-04-07T19:50:40.602Z",
    "level": "info",
    "category": "SYSTEM",
    "message": "System: health_check",
    "metadata": {
      "event": "health_check",
      "overallStatus": "healthy",
      "responseTime": 1950,
      "services": {
        "authentik": "up",
        "ldap": "up",
        "database": "up",
        "smtp": "up"
      }
    }
  },
  {
    "id": "1775591272331-vcvwx2s8b",
    "timestamp": "2026-04-07T19:47:52.331Z",
    "level": "info",
    "category": "SYSTEM",
    "message": "System: health_check",
    "metadata": {
      "event": "health_check",
      "overallStatus": "healthy",
      "responseTime": 500,
      "services": {
        "authentik": "up",
        "ldap": "up",
        "database": "up",
        "smtp": "up"
      }
    }
  },
  {
    "id": "1775591231393-x4q1whc5h",
    "timestamp": "2026-04-07T19:47:11.393Z",
    "level": "info",
    "category": "SYSTEM",
    "message": "System: health_check",
    "metadata": {
      "event": "health_check",
      "overallStatus": "healthy",
      "responseTime": 2418,
      "services": {
        "authentik": "up",
        "ldap": "up",
        "database": "up",
        "smtp": "up"
      }
    }
  },
  {
    "id": "1775590212269-4b5smk53f",
    "timestamp": "2026-04-07T19:30:12.269Z",
    "level": "info",
    "category": "SYSTEM",
    "message": "System: health_check",
    "metadata": {
      "event": "health_check",
      "overallStatus": "healthy",
      "responseTime": 474,
      "services": {
        "authentik": "up",
        "ldap": "up",
        "database": "up",
        "smtp": "up"
      }
    }
  },
  {
    "id": "1775590110989-nwbvsn5d2",
    "timestamp": "2026-04-07T19:28:30.989Z",
    "level": "info",
    "category": "SYSTEM",
    "message": "System: health_check",
    "metadata": {
      "event": "health_check",
      "overallStatus": "healthy",
      "responseTime": 524,
      "services": {
        "authentik": "up",
        "ldap": "up",
        "database": "up",
        "smtp": "up"
      }
    }
  },
  {
    "id": "1775590079332-g3t1m45c7",
    "timestamp": "2026-04-07T19:27:59.332Z",
    "level": "info",
    "category": "SYSTEM",
    "message": "System: health_check",
    "metadata": {
      "event": "health_check",
      "overallStatus": "healthy",
      "responseTime": 2596,
      "services": {
        "authentik": "up",
        "ldap": "up",
        "database": "up",
        "smtp": "up"
      }
    }
  },
  {
    "id": "1775589432721-ufh1tr4bk",
    "timestamp": "2026-04-07T19:17:12.721Z",
    "level": "info",
    "category": "SYSTEM",
    "message": "System: health_check",
    "metadata": {
      "event": "health_check",
      "overallStatus": "healthy",
      "responseTime": 3308,
      "services": {
        "authentik": "up",
        "ldap": "up",
        "database": "up",
        "smtp": "up"
      }
    }
  },
  {
    "id": "1775588357568-zz881gr0z",
    "timestamp": "2026-04-07T18:59:17.568Z",
    "level": "info",
    "category": "SYSTEM",
    "message": "System: health_check",
    "metadata": {
      "event": "health_check",
      "overallStatus": "healthy",
      "responseTime": 1793,
      "services": {
        "authentik": "up",
        "ldap": "up",
        "database": "up",
        "smtp": "up"
      }
    }
  },
  {
    "id": "1775588129440-m9w830dbr",
    "timestamp": "2026-04-07T18:55:29.440Z",
    "level": "info",
    "category": "SYSTEM",
    "message": "System: service_test",
    "metadata": {
      "event": "service_test",
      "service": "smtp",
      "status": "up",
      "latency": 517
    }
  },
  {
    "id": "1775588127783-1mj03mi3m",
    "timestamp": "2026-04-07T18:55:27.783Z",
    "level": "info",
    "category": "SYSTEM",
    "message": "System: service_test",
    "metadata": {
      "event": "service_test",
      "service": "database",
      "latency": 3
    }
  },
  {
    "id": "1775588126683-o1pz59cto",
    "timestamp": "2026-04-07T18:55:26.683Z",
    "level": "info",
    "category": "SYSTEM",
    "message": "System: service_test",
    "metadata": {
      "event": "service_test",
      "service": "ldap",
      "status": "up",
      "latency": 3
    }
  },
  {
    "id": "1775588125502-47xxvx6h7",
    "timestamp": "2026-04-07T18:55:25.502Z",
    "level": "info",
    "category": "SYSTEM",
    "message": "System: service_test",
    "metadata": {
      "event": "service_test",
      "service": "authentik",
      "status": "up",
      "latency": 160
    }
  },
  {
    "id": "1775588109922-t0dcnepjv",
    "timestamp": "2026-04-07T18:55:09.922Z",
    "level": "info",
    "category": "SYSTEM",
    "message": "System: service_test",
    "metadata": {
      "event": "service_test",
      "service": "smtp",
      "status": "up",
      "latency": 516
    }
  },
  {
    "id": "1775588106339-qy1oghg15",
    "timestamp": "2026-04-07T18:55:06.339Z",
    "level": "info",
    "category": "SYSTEM",
    "message": "System: service_test",
    "metadata": {
      "event": "service_test",
      "service": "database",
      "latency": 2
    }
  },
  {
    "id": "1775588100873-4qpftri3y",
    "timestamp": "2026-04-07T18:55:00.873Z",
    "level": "info",
    "category": "SYSTEM",
    "message": "System: service_test",
    "metadata": {
      "event": "service_test",
      "service": "authentik",
      "status": "up",
      "latency": 150
    }
  },
  {
    "id": "1775588097801-23tehnhbq",
    "timestamp": "2026-04-07T18:54:57.801Z",
    "level": "info",
    "category": "SYSTEM",
    "message": "System: service_test",
    "metadata": {
      "event": "service_test",
      "service": "ldap",
      "status": "up",
      "latency": 4
    }
  },
  {
    "id": "1775588094285-on99jjrpe",
    "timestamp": "2026-04-07T18:54:54.285Z",
    "level": "info",
    "category": "SYSTEM",
    "message": "System: health_check",
    "metadata": {
      "event": "health_check",
      "overallStatus": "healthy",
      "responseTime": 2295,
      "services": {
        "authentik": "up",
        "ldap": "up",
        "database": "up",
        "smtp": "up"
      }
    }
  },
  {
    "id": "1775587878857-ajhrqfwa9",
    "timestamp": "2026-04-07T18:51:18.857Z",
    "level": "info",
    "category": "SYSTEM",
    "message": "System: health_check",
    "metadata": {
      "event": "health_check",
      "overallStatus": "healthy",
      "responseTime": 493,
      "services": {
        "authentik": "up",
        "ldap": "up",
        "database": "up",
        "smtp": "up"
      }
    }
  },
  {
    "id": "1775587874026-be5lxgkyl",
    "timestamp": "2026-04-07T18:51:14.025Z",
    "level": "info",
    "category": "SYSTEM",
    "message": "System: health_check",
    "metadata": {
      "event": "health_check",
      "overallStatus": "healthy",
      "responseTime": 5807,
      "services": {
        "authentik": "up",
        "ldap": "up",
        "database": "up",
        "smtp": "up"
      }
    }
  },
  {
    "id": "1775585285672-6aqsw3w4p",
    "timestamp": "2026-04-07T18:08:05.672Z",
    "level": "info",
    "category": "SYSTEM",
    "message": "System: service_test",
    "metadata": {
      "event": "service_test",
      "service": "smtp",
      "status": "up",
      "latency": 583
    }
  },
  {
    "id": "1775585266373-c7aeyttjl",
    "timestamp": "2026-04-07T18:07:46.373Z",
    "level": "info",
    "category": "SYSTEM",
    "message": "System: service_test",
    "metadata": {
      "event": "service_test",
      "service": "smtp",
      "status": "down",
      "latency": 4402
    }
  },
  {
    "id": "1775585240389-l6plssl1p",
    "timestamp": "2026-04-07T18:07:20.389Z",
    "level": "info",
    "category": "SYSTEM",
    "message": "System: service_test",
    "metadata": {
      "event": "service_test",
      "service": "smtp",
      "status": "down",
      "latency": 509
    }
  },
  {
    "id": "1775585212330-ltgpizs85",
    "timestamp": "2026-04-07T18:06:52.330Z",
    "level": "info",
    "category": "SYSTEM",
    "message": "System: service_test",
    "metadata": {
      "event": "service_test",
      "service": "smtp",
      "status": "down",
      "latency": 10007
    }
  },
  {
    "id": "1775585186609-1ewjyhn2h",
    "timestamp": "2026-04-07T18:06:26.609Z",
    "level": "info",
    "category": "SYSTEM",
    "message": "System: service_test",
    "metadata": {
      "event": "service_test",
      "service": "smtp",
      "status": "down",
      "latency": 10010
    }
  },
  {
    "id": "1775585171165-pxox8bp67",
    "timestamp": "2026-04-07T18:06:11.165Z",
    "level": "info",
    "category": "SYSTEM",
    "message": "System: service_test",
    "metadata": {
      "event": "service_test",
      "service": "smtp",
      "status": "down",
      "latency": 8319
    }
  },
  {
    "id": "1775585141800-lfn5y9f3b",
    "timestamp": "2026-04-07T18:05:41.800Z",
    "level": "info",
    "category": "SYSTEM",
    "message": "System: service_test",
    "metadata": {
      "event": "service_test",
      "service": "smtp",
      "status": "down",
      "latency": 5031
    }
  },
  {
    "id": "1775585113716-qhbnhs8ag",
    "timestamp": "2026-04-07T18:05:13.716Z",
    "level": "info",
    "category": "SYSTEM",
    "message": "System: health_check",
    "metadata": {
      "event": "health_check",
      "overallStatus": "healthy",
      "responseTime": 173,
      "services": {
        "authentik": "up",
        "ldap": "up",
        "database": "up",
        "smtp": "down"
      }
    }
  }
]